picoolfx-0.1.1.dist-info/METADATA
picoolfx-0.1.1.dist-info/WHEEL
picoolfx-0.1.1.dist-info/licenses/LICENSE.txt
picoolfx/__init__.py
picoolfx/picoolfx.py
picoolfx/utils.py
picoolfx-0.1.1.dist-info/RECORD
