Metadata-Version: 2.1
Name: picoolfx
Version: 0.1.1
Summary: A small package that applies nice effects to images
Author-Email: Nicola Cerutti <nc@nicores.de>
Classifier: Programming Language :: Python :: 3
Classifier: License :: OSI Approved :: MIT License
Classifier: Operating System :: OS Independent
Project-URL: Homepage, https://github.com/ncerutti/picoolfx
Project-URL: Bug tracker, https://github.com/ncerutti/picoolfx/issues
Requires-Python: >=3.7
Requires-Dist: geopandas
Requires-Dist: matplotlib
Requires-Dist: noise
Requires-Dist: numpy
Requires-Dist: pandas
Requires-Dist: Pillow
Requires-Dist: rasterio
Requires-Dist: Shapely
